README.md
setup.py
allplay/__init__.py
allplay/__main__.py
allplay/allplay.py
allplay/config.py
allplay/database.py
allplay/interface.py
allplay/library.py
allplay/media.py
allplay.egg-info/PKG-INFO
allplay.egg-info/SOURCES.txt
allplay.egg-info/dependency_links.txt
allplay.egg-info/entry_points.txt
allplay.egg-info/requires.txt
allplay.egg-info/top_level.txt