Metadata-Version: 1.0
Name: allplay
Version: 0.1.0
Summary: Manage while you consume media manager
Home-page: https://github.com/cheethoe/allplay
Author: Michael Hsu
Author-email: cheeto@gmail.com
License: UNKNOWN
Platform: UNKNOWN
